{
    "url": {
        "data": "http:\/\/cdcb.judicial.gov.tw\/abbs\/wkw\/WHD6K03.jsp?ab=AAAdkxAAHAAAChDAAH&bc=076&cd=%AA%6B%B5%6E++++++++++++++++&de=000018&ef=TPD&fg=1",
        "staff": "http:\/\/cdcb.judicial.gov.tw\/abbs\/wkw\/WHD6K04.jsp?ab=AAAdkxAAHAAAChDAAH&bc=076&cd=%AA%6B%B5%6E++++++++++++++++&de=000018&ef=TPD&fg=1",
        "office": "http:\/\/cdcb.judicial.gov.tw\/abbs\/wkw\/WHD6K07.jsp?ab=AAAdkxAAHAAAChDAAH&bc=076&cd=%AA%6B%B5%6E++++++++++++++++&de=000018&ef=TPD&fg=1"
    },
    "登記案號": "076年法登字18號",
    "類別": "財團",
    "案由": "設立登記",
    "主任": "林貴美",
    "登記號數": "1218",
    "收件日期": "076\/09\/04",
    "登記日期": "076\/09\/04",
    "公告日期": "076\/09\/04",
    "登記簿": "51冊55頁",
    "任期判定": "",
    "屆期判定": "0",
    "法人代表": "蔡坤山",
    "法人名稱": "財團法人台灣區養殖蝦類發展基金會",
    "設立登記日期": "076\/09\/04",
    "主事務所": "台北市青島東路一之三號二樓",
    "目的": "促進台灣區養殖蝦類各業之團結合作，研究提算養蝦及加工技術，提高產品品質，拓展市場，謀求養殖事業之發展，維護養殖，加工業者共同之利益為宗旨。",
    "捐助方法": "由行政院農業委員會、台灣省漁會、台灣區冷凍水產工業同業會及養蝦業者等捐助",
    "許可機關日期": "行政院農業委員會七十六年七月二十九日︵七六︶農漁字第四七九五四號函",
    "存立時期": "永久",
    "財產總額": "13180000",
    "結案原因": "准許",
    "結案日期": "076\/09\/04",
    "歸檔日期": "076\/09\/04",
    "發證日期": "",
    "送達代收人姓名": "",
    "送達代收人住址": "",
    "郵遞區號": "",
    "清算人": "",
    "註銷日期": "",
    "撤銷日期": "",
    "撤(註)銷機關文號": "",
    "撤(註)銷原因": "",
    "董監事": [
        [
            "董事長",
            "蔡坤山"
        ]
    ],
    "分事務所": [

    ],
    "latitude": "",
    "longitude": ""
}