{
    "登記案號": "097年法登他字42號",
    "類別": "社團",
    "案由": "變更登記",
    "主任": "李秋瓊",
    "登記號數": "1498",
    "收件日期": "097\/02\/19",
    "登記日期": "097\/02\/19",
    "公告日期": "097\/02\/19",
    "登記簿": "32冊18頁",
    "任期判定": "2",
    "屆期判定": "3",
    "法人代表": "蕭祥修",
    "法人名稱": "社團法人台中市教會發展策略聯盟協會",
    "設立登記日期": "095\/12\/29",
    "主事務所": "臺中市大雅路３３７號８樓",
    "目的": "以推動城市基督教會聯結、開拓新教會及研發教會更新為宗旨，並透過教會的發展更新帶動城市及社區民眾的心靈更新。",
    "捐助方法": "會員會費等",
    "許可機關日期": "臺中市政府中華民國９０年６月１９日",
    "存立時期": "永久",
    "財產總額": "1015207",
    "結案原因": "准許",
    "結案日期": "097\/02\/19",
    "歸檔日期": "097\/03\/05",
    "發證日期": "097\/02\/19",
    "送達代收人姓名": "陳麗安",
    "送達代收人住址": "電話:0422984811轉275",
    "郵遞區號": "",
    "清算人": "",
    "註銷日期": "",
    "撤銷日期": "",
    "撤(註)銷機關文號": "",
    "撤(註)銷原因": "",
    "董監事": [
        [
            "常務理事",
            "杜明達"
        ],
        [
            "監事",
            "高臨榮"
        ],
        [
            "理事長",
            "蕭祥修"
        ],
        [
            "常務理事",
            "吳政宏"
        ],
        [
            "常務理事",
            "馮隆曦"
        ],
        [
            "理事",
            "廖昆田"
        ],
        [
            "理事",
            "林世平"
        ],
        [
            "理事",
            "黃清塗"
        ],
        [
            "理事",
            "羅劍保"
        ],
        [
            "理事",
            "李麗珍"
        ],
        [
            "理事",
            "何宗杰"
        ],
        [
            "常務理事",
            "林進泰"
        ],
        [
            "理事",
            "廖金河"
        ],
        [
            "常務監事",
            "潘信宏"
        ],
        [
            "理事",
            "何中輔"
        ],
        [
            "監事",
            "馮同強"
        ],
        [
            "監事",
            "劉紀"
        ],
        [
            "理事",
            "歐陽輝"
        ]
    ],
    "分事務所": [

    ],
    "latitude": "24.165459000000",
    "longitude": "120.673552400000"
}