{
    "登記案號": "085年法登他字506號",
    "類別": "財團",
    "案由": "變更登記",
    "主任": "張茂寅",
    "登記號數": "268",
    "收件日期": "085\/09\/12",
    "登記日期": "085\/09\/25",
    "公告日期": "085\/09\/25",
    "登記簿": "19冊5頁",
    "任期判定": "1",
    "屆期判定": "20",
    "法人代表": "各董事",
    "法人名稱": "財團法人臺灣省物資局職工福利委員會",
    "設立登記日期": "055\/05\/16",
    "主事務所": "台北市開封街一段三號",
    "目的": "為增進職工之福利，依照職工福利金條例第一條之規定，辦理職工福利事業。",
    "捐助方法": "依照員工福利金條例第二條第一項、第四項及營業收入總額提撥",
    "許可機關日期": "臺灣省政府社會處五十四年十月二十九日　府一字第二八一七五號函",
    "存立時期": "永久",
    "財產總額": "46045300",
    "結案原因": "准許",
    "結案日期": "085\/09\/25",
    "歸檔日期": "085\/10\/04",
    "發證日期": "085\/10\/04",
    "送達代收人姓名": "",
    "送達代收人住址": "",
    "郵遞區號": "",
    "清算人": "",
    "註銷日期": "",
    "撤銷日期": "",
    "撤(註)銷機關文號": "",
    "撤(註)銷原因": "",
    "董監事": [
        [
            "董事長",
            "陳清泉"
        ],
        [
            "董事",
            "張麗堂"
        ],
        [
            "董事",
            "林忠賢"
        ],
        [
            "董事",
            "徐石柳"
        ],
        [
            "董事",
            "盧兆明"
        ],
        [
            "董事",
            "邱素梅"
        ],
        [
            "董事",
            "王火木"
        ],
        [
            "董事",
            "蔡貴貞"
        ],
        [
            "董事",
            "蘇志堅"
        ],
        [
            "董事",
            "陳炳源"
        ],
        [
            "董事",
            "劉志誠"
        ],
        [
            "董事",
            "傅必成"
        ]
    ],
    "分事務所": [

    ],
    "latitude": "25.046054200000",
    "longitude": "121.514410300000"
}