{
    "登記案號": "081年法登字154號",
    "類別": "財團",
    "案由": "變更登記",
    "主任": "謝怜聰",
    "登記號數": "154",
    "收件日期": "081\/01\/16",
    "登記日期": "081\/10\/12",
    "公告日期": "081\/10\/20",
    "登記簿": "8冊62頁",
    "任期判定": "",
    "屆期判定": "6",
    "法人代表": "董事長",
    "法人名稱": "財團法人台灣省新竹市彭氏祖祠管理委員會",
    "設立登記日期": "064\/03\/07",
    "主事務所": "新竹市南寮里東大路三段四六七巷一號",
    "目的": "本會以奉祀開基始祖商賢大夫以錢鏗公暨歷代烈祖烈宗之神位,闡揚祖德、敦親睦族、追思祖德扶植後裔並宏揚復興中華文化為宗旨",
    "捐助方法": "捐助",
    "許可機關日期": "六十四年一月八日新竹縣政府",
    "存立時期": "無限期",
    "財產總額": "398119",
    "結案原因": "准許",
    "結案日期": "081\/10\/12",
    "歸檔日期": "092\/12\/24",
    "發證日期": "",
    "送達代收人姓名": "",
    "送達代收人住址": "",
    "郵遞區號": "",
    "清算人": "",
    "註銷日期": "",
    "撤銷日期": "",
    "撤(註)銷機關文號": "",
    "撤(註)銷原因": "",
    "董監事": [
        [
            "董事長",
            "彭根旺"
        ],
        [
            "常務董事",
            "彭國全"
        ],
        [
            "常務董事",
            "彭淮澤"
        ],
        [
            "常務董事",
            "彭金火"
        ],
        [
            "董事",
            "彭定雄"
        ],
        [
            "董事",
            "彭謙詐"
        ],
        [
            "董事",
            "彭錦棟"
        ],
        [
            "董事",
            "彭世清"
        ],
        [
            "董事",
            "彭合興"
        ],
        [
            "董事",
            "彭武雄"
        ],
        [
            "董事",
            "彭傳灶"
        ],
        [
            "董事",
            "彭清南"
        ],
        [
            "董事",
            "彭仁德"
        ],
        [
            "董事",
            "彭振堂"
        ],
        [
            "監事",
            "彭金福"
        ]
    ],
    "分事務所": [

    ],
    "latitude": "24.835972000000",
    "longitude": "120.945222000000"
}