{
    "url": {
        "data": "http:\/\/cdcb.judicial.gov.tw\/abbs\/wkw\/WHD6K03.jsp?ab=AAAdkxAAHAAAChDAAA&bc=076&cd=%AA%6B%B5%6E++++++++++++++++&de=000004&ef=TPD&fg=1",
        "staff": "http:\/\/cdcb.judicial.gov.tw\/abbs\/wkw\/WHD6K04.jsp?ab=AAAdkxAAHAAAChDAAA&bc=076&cd=%AA%6B%B5%6E++++++++++++++++&de=000004&ef=TPD&fg=1",
        "office": "http:\/\/cdcb.judicial.gov.tw\/abbs\/wkw\/WHD6K07.jsp?ab=AAAdkxAAHAAAChDAAA&bc=076&cd=%AA%6B%B5%6E++++++++++++++++&de=000004&ef=TPD&fg=1"
    },
    "登記案號": "076年法登字4號",
    "類別": "財團",
    "案由": "設立登記",
    "主任": "林貴美",
    "登記號數": "1198",
    "收件日期": "076\/04\/16",
    "登記日期": "076\/04\/16",
    "公告日期": "076\/04\/16",
    "登記簿": "51冊15頁",
    "任期判定": "",
    "屆期判定": "0",
    "法人代表": "闕文裕",
    "法人名稱": "財團法人台北市基督教台灣神的教會佳美堂",
    "設立登記日期": "076\/04\/16",
    "主事務所": "台北市龍江路二二九巷三之一號一樓",
    "目的": "宣揚基督教教義，辦理社會公益慈善教育事業。",
    "捐助方法": "由羅霆松牧師捐助",
    "許可機關日期": "台北市政府民政局七十六年三月十八日︵七六︶北市民三字第四０九二號函",
    "存立時期": "永久",
    "財產總額": "1703244",
    "結案原因": "准許",
    "結案日期": "076\/11\/16",
    "歸檔日期": "076\/11\/16",
    "發證日期": "",
    "送達代收人姓名": "",
    "送達代收人住址": "",
    "郵遞區號": "",
    "清算人": "",
    "註銷日期": "",
    "撤銷日期": "",
    "撤(註)銷機關文號": "",
    "撤(註)銷原因": "",
    "董監事": [

    ],
    "分事務所": [

    ],
    "latitude": "",
    "longitude": ""
}