{
    "url": {
        "data": "http:\/\/cdcb.judicial.gov.tw\/abbs\/wkw\/WHD6K03.jsp?ab=AAAdkxAAHAAAGFnAAJ&bc=101&cd=%AA%6B%B5%6E%AA%C0++++++++++++++&de=000025&ef=TYD&fg=1",
        "staff": "http:\/\/cdcb.judicial.gov.tw\/abbs\/wkw\/WHD6K04.jsp?ab=AAAdkxAAHAAAGFnAAJ&bc=101&cd=%AA%6B%B5%6E%AA%C0++++++++++++++&de=000025&ef=TYD&fg=1",
        "office": "http:\/\/cdcb.judicial.gov.tw\/abbs\/wkw\/WHD6K07.jsp?ab=AAAdkxAAHAAAGFnAAJ&bc=101&cd=%AA%6B%B5%6E%AA%C0++++++++++++++&de=000025&ef=TYD&fg=1"
    },
    "登記案號": "101年法登社字25號",
    "類別": "社團",
    "案由": "設立登記",
    "主任": "林蕙鴻",
    "登記號數": "895",
    "收件日期": "101\/07\/05",
    "登記日期": "101\/07\/17",
    "公告日期": "101\/07\/17",
    "登記簿": "19冊39頁",
    "任期判定": "",
    "屆期判定": "",
    "法人代表": "王正行",
    "法人名稱": "社團法人桃園縣懷恩傳愛社區關懷協會",
    "設立登記日期": "101\/07\/17",
    "主事務所": "桃園縣平鎮市環南路2段27號8樓之1",
    "目的": "本會為依法設立、非以營利為目的之社會團體，以社區關懷為宗旨。我們的宗旨在於「讓愛傳出去」，本著「互相關懷、尊重生命、家庭有愛、社會祥和」的精神，秉持人飢己飢、人溺人溺的理念，透過實際服務、活動、宣導、協助辦理貧困兒童、老年人、身心障礙及原住民之福利與濟助等等。期望集合眾善心人之力量，使生命更加美好，家庭更加幸福，社會更加祥和。",
    "捐助方法": "會費等",
    "許可機關日期": "桃園縣政府中華民國101年5月11日府社發字第1010114971號函",
    "存立時期": "永久",
    "財產總額": "0",
    "結案原因": "准許",
    "結案日期": "101\/07\/17",
    "歸檔日期": "",
    "發證日期": "",
    "送達代收人姓名": "",
    "送達代收人住址": "",
    "郵遞區號": "",
    "清算人": "",
    "註銷日期": "",
    "撤銷日期": "",
    "撤(註)銷機關文號": "",
    "撤(註)銷原因": "",
    "董監事": [
        [
            "理事長",
            "王正行"
        ],
        [
            "理事",
            "曾弘慈"
        ],
        [
            "理事",
            "王荹雄"
        ],
        [
            "理事",
            "徐阿玉"
        ],
        [
            "理事",
            "林正明"
        ],
        [
            "理事",
            "張林阿惜"
        ],
        [
            "理事",
            "黃約珥"
        ],
        [
            "理事",
            "林秀英"
        ],
        [
            "理事",
            "陳福生"
        ],
        [
            "常務監事",
            "邱凡恩"
        ],
        [
            "監事",
            "楊光志"
        ],
        [
            "監事",
            "胡清春"
        ]
    ],
    "分事務所": [

    ],
    "latitude": "",
    "longitude": ""
}