{
    "登記案號": "077年登字216號",
    "類別": "財團",
    "案由": "設立登記",
    "主任": "林貴美",
    "登記號數": "1316",
    "收件日期": "077\/09\/12",
    "登記日期": "077\/09\/12",
    "公告日期": "077\/09\/12",
    "登記簿": "55冊15頁",
    "任期判定": "",
    "屆期判定": "",
    "法人代表": "謝生富",
    "法人名稱": "財團法人大中法律文教基金會",
    "設立登記日期": "077\/09\/12",
    "主事務所": "台北市復興南路1段129號16樓",
    "目的": "本會以宏揚法治，服務社會，造福人群為宗旨，辦理有關法律之服務、研究及其獎助事宜。",
    "捐助方法": "本會設立基金共新台幣壹佰貳拾萬元整，由謝生富捐助。俟本會依法完成財團法人登記後，得繼續接受捐助。",
    "許可機關日期": "法務部中華民國77年7月29日法77保字第12451號函",
    "存立時期": "永久",
    "財產總額": "1200000",
    "結案原因": "准許",
    "結案日期": "077\/09\/12",
    "歸檔日期": "077\/09\/20",
    "發證日期": "077\/09\/14",
    "送達代收人姓名": "",
    "送達代收人住址": "",
    "郵遞區號": "",
    "清算人": "",
    "註銷日期": "",
    "撤銷日期": "",
    "撤(註)銷機關文號": "",
    "撤(註)銷原因": "",
    "董監事": [
        [
            "董事長",
            "謝生富"
        ],
        [
            "董事",
            "蕭振宗"
        ],
        [
            "董事",
            "謝黃麗玉"
        ],
        [
            "董事",
            "王朝慶"
        ],
        [
            "董事",
            "林富男"
        ],
        [
            "董事",
            "沈慶京"
        ],
        [
            "董事",
            "林國雄"
        ],
        [
            "董事",
            "黃樹和"
        ],
        [
            "董事",
            "李連清"
        ],
        [
            "董事",
            "賴錦墩"
        ],
        [
            "董事",
            "張光瑤"
        ],
        [
            "董事",
            "施西田"
        ],
        [
            "董事",
            "蕭柏煌"
        ]
    ],
    "分事務所": [

    ],
    "latitude": "",
    "longitude": ""
}