{
    "url": {
        "data": "http:\/\/cdcb.judicial.gov.tw\/abbs\/wkw\/WHD6K03.jsp?ab=AAAdkxAAHAAAGK6AAH&bc=101&cd=%AA%6B%B5%6E%A5%4C++++++++++++++&de=000209&ef=TND&fg=1",
        "staff": "http:\/\/cdcb.judicial.gov.tw\/abbs\/wkw\/WHD6K04.jsp?ab=AAAdkxAAHAAAGK6AAH&bc=101&cd=%AA%6B%B5%6E%A5%4C++++++++++++++&de=000209&ef=TND&fg=1",
        "office": "http:\/\/cdcb.judicial.gov.tw\/abbs\/wkw\/WHD6K07.jsp?ab=AAAdkxAAHAAAGK6AAH&bc=101&cd=%AA%6B%B5%6E%A5%4C++++++++++++++&de=000209&ef=TND&fg=1"
    },
    "登記案號": "101年法登他字209號",
    "類別": "社團",
    "案由": "解散及清算人任免",
    "主任": "秦建華",
    "登記號數": "505",
    "收件日期": "101\/09\/07",
    "登記日期": "101\/09\/07",
    "公告日期": "101\/09\/10",
    "登記簿": "34冊7頁",
    "任期判定": "1",
    "屆期判定": "5",
    "法人代表": "林雨瑢",
    "法人名稱": "社團法人台南市身心障礙者福利協進會",
    "設立登記日期": "090\/02\/26",
    "主事務所": "台南市南區新都路５２０巷６７號５樓",
    "目的": "一、配合相關部門協助身心障礙者解決就業、就學、就養。二、依現有福利政策，配合民間資源成立庇護性工廠、商店農場。三、舉辦各類觀摩、考察活動，促進身心障礙者交流。四、不定期舉辦各類研討會以瞭解身心障礙者之需要。五、協助身心障礙者申請補助購置輔具。六、不定期舉辦志工、義工及專業人員之培訓與在職訓練。七、提供各障別及年齡層之身心障礙者必要之服務。八、成立身心障礙者人力資源中心，以落實解決本市身心障礙者之就業問題。九、凡與身心障礙者相關之事項，本會均得視其必要性適時提供必要之措施。",
    "捐助方法": "會員繳納會費或其捐款",
    "許可機關日期": "台南市政府九十年一月三十日南市社行字第五九四二號",
    "存立時期": "永久",
    "財產總額": "1000",
    "結案原因": "准許",
    "結案日期": "101\/09\/10",
    "歸檔日期": "",
    "發證日期": "",
    "送達代收人姓名": "",
    "送達代收人住址": "",
    "郵遞區號": "",
    "清算人": "",
    "註銷日期": "",
    "撤銷日期": "",
    "撤(註)銷機關文號": "",
    "撤(註)銷原因": "",
    "董監事": [
        [
            "常務理事",
            "李燣成"
        ],
        [
            "監事",
            "金廣範"
        ],
        [
            "常務理事",
            "陳景章"
        ],
        [
            "理事",
            "謝麗容"
        ],
        [
            "理事",
            "黃謝金鳳"
        ],
        [
            "理事",
            "董文良"
        ],
        [
            "常務監事",
            "張金玉"
        ],
        [
            "理事",
            "林志恭"
        ],
        [
            "監事",
            "林金龍"
        ],
        [
            "清算人",
            "林雨瑢"
        ],
        [
            "理事",
            "程丁順"
        ],
        [
            "理事",
            "張幸生"
        ]
    ],
    "分事務所": [

    ],
    "latitude": "",
    "longitude": ""
}