{
    "登記案號": "089年法登社字3號",
    "類別": "社團",
    "案由": "設立登記",
    "主任": "陳茂哲",
    "登記號數": "674",
    "收件日期": "089\/01\/05",
    "登記日期": "089\/01\/10",
    "公告日期": "089\/01\/10",
    "登記簿": "24冊17頁",
    "任期判定": "",
    "屆期判定": "",
    "法人代表": "各理事",
    "法人名稱": "社團法人中國造船暨輪機工程師學會",
    "設立登記日期": "089\/01\/10",
    "主事務所": "台北市大安區舟山路七十三號",
    "目的": "以聯絡造船及輪機工程師研究造船及輪機工程學術，協力發展造船暨輪機工程事業為宗旨。",
    "捐助方法": "入會費、常年會費",
    "許可機關日期": "內政部中華民國八十八年十二月十八日台?|內社字第八八四一四八六號函",
    "存立時期": "永久",
    "財產總額": "5808000",
    "結案原因": "准許",
    "結案日期": "089\/01\/10",
    "歸檔日期": "089\/01\/17",
    "發證日期": "089\/01\/17",
    "送達代收人姓名": "",
    "送達代收人住址": "",
    "郵遞區號": "",
    "清算人": "",
    "註銷日期": "",
    "撤銷日期": "",
    "撤(註)銷機關文號": "",
    "撤(註)銷原因": "",
    "董監事": [
        [
            "理事長",
            "李雅榮"
        ],
        [
            "常務理事",
            "張和男"
        ],
        [
            "常務理事",
            "張旭勇"
        ],
        [
            "常務理事",
            "蔡定邦"
        ],
        [
            "常務理事",
            "王偉輝"
        ],
        [
            "理事",
            "陳生平"
        ],
        [
            "理事",
            "劉武顯"
        ],
        [
            "理事",
            "邵揮洲"
        ],
        [
            "理事",
            "黃守真"
        ],
        [
            "理事",
            "邱逢琛"
        ],
        [
            "理事",
            "韓碧祥"
        ],
        [
            "理事",
            "黃太平"
        ],
        [
            "理事",
            "林允進"
        ],
        [
            "理事",
            "鄧運連"
        ],
        [
            "理事",
            "陳慶男"
        ],
        [
            "理事",
            "郭興家"
        ],
        [
            "理事",
            "吳俊仁"
        ],
        [
            "理事",
            "夏曉文"
        ],
        [
            "理事",
            "李文溪"
        ],
        [
            "理事",
            "黃明敏"
        ],
        [
            "理事",
            "呂祟湧"
        ],
        [
            "監事",
            "梁卓中"
        ],
        [
            "監事",
            "陳重盛"
        ],
        [
            "監事",
            "朱于益"
        ],
        [
            "監事",
            "葉宣橫"
        ]
    ],
    "分事務所": [

    ]
}