{
    "url": {
        "data": "http:\/\/cdcb.judicial.gov.tw\/abbs\/wkw\/WHD6K03.jsp?ab=AAAdkxAAHAAAIqCAAK&bc=097&cd=%AA%6B%B5%6E%A5%4C++++++++++++++&de=000052&ef=TYD&fg=1",
        "staff": "http:\/\/cdcb.judicial.gov.tw\/abbs\/wkw\/WHD6K04.jsp?ab=AAAdkxAAHAAAIqCAAK&bc=097&cd=%AA%6B%B5%6E%A5%4C++++++++++++++&de=000052&ef=TYD&fg=1",
        "office": "http:\/\/cdcb.judicial.gov.tw\/abbs\/wkw\/WHD6K07.jsp?ab=AAAdkxAAHAAAIqCAAK&bc=097&cd=%AA%6B%B5%6E%A5%4C++++++++++++++&de=000052&ef=TYD&fg=1"
    },
    "登記案號": "097年法登他字52號",
    "類別": "財團",
    "案由": "變更登記",
    "主任": "林光輝",
    "登記號數": "521",
    "收件日期": "097\/04\/11",
    "登記日期": "097\/04\/21",
    "公告日期": "097\/04\/21",
    "登記簿": "11冊95頁",
    "任期判定": "2",
    "屆期判定": "2",
    "法人代表": "龍應台",
    "法人名稱": "財團法人龍應台文化基金會",
    "設立登記日期": "094\/05\/20",
    "主事務所": "桃園市介壽路288號8樓",
    "目的": "以建立開創的文化典範為宗旨。",
    "捐助方法": "捐助",
    "許可機關日期": "桃園縣政府文化局中華民國94年5月3日桃縣文發字第0941001940號",
    "存立時期": "永久",
    "財產總額": "2000000",
    "結案原因": "准許",
    "結案日期": "097\/04\/22",
    "歸檔日期": "097\/06\/11",
    "發證日期": "097\/05\/19",
    "送達代收人姓名": "",
    "送達代收人住址": "",
    "郵遞區號": "",
    "清算人": "",
    "註銷日期": "",
    "撤銷日期": "",
    "撤(註)銷機關文號": "",
    "撤(註)銷原因": "",
    "董監事": [
        [
            "董事長",
            "龍應台"
        ],
        [
            "董事",
            "王杏慶"
        ],
        [
            "董事",
            "王榮文"
        ],
        [
            "董事",
            "曾志朗"
        ],
        [
            "董事",
            "楊憲卿"
        ],
        [
            "董事",
            "劉炯朗"
        ],
        [
            "董事",
            "劉維琪"
        ],
        [
            "董事",
            "嚴長壽"
        ],
        [
            "董事",
            "陳浩"
        ]
    ],
    "分事務所": [

    ],
    "latitude": "",
    "longitude": ""
}