{
    "url": {
        "data": "http:\/\/cdcb.judicial.gov.tw\/abbs\/wkw\/WHD6K03.jsp?ab=AAAdkxAAHAAAGzrAAE&bc=097&cd=%AA%6B%B5%6E%A5%4C++++++++++++++&de=000239&ef=SLD&fg=1",
        "staff": "http:\/\/cdcb.judicial.gov.tw\/abbs\/wkw\/WHD6K04.jsp?ab=AAAdkxAAHAAAGzrAAE&bc=097&cd=%AA%6B%B5%6E%A5%4C++++++++++++++&de=000239&ef=SLD&fg=1",
        "office": "http:\/\/cdcb.judicial.gov.tw\/abbs\/wkw\/WHD6K07.jsp?ab=AAAdkxAAHAAAGzrAAE&bc=097&cd=%AA%6B%B5%6E%A5%4C++++++++++++++&de=000239&ef=SLD&fg=1"
    },
    "登記案號": "097年法登他字239號",
    "類別": "財團",
    "案由": "變更登記",
    "主任": "簡福助",
    "登記號數": "398",
    "收件日期": "097\/07\/15",
    "登記日期": "097\/07\/16",
    "公告日期": "097\/07\/18",
    "登記簿": "20冊15頁",
    "任期判定": "2",
    "屆期判定": "7",
    "法人代表": "劉叔康",
    "法人名稱": "財團法人擊樂文教基金會",
    "設立登記日期": "078\/05\/04",
    "主事務所": "台北市北投區大業路10號地下1樓",
    "目的": "結合政府、文化界與企業界，共同促進文化藝術之研究發展，協助推動音樂專業化，國際化、普及化，以提昇藝術表演演奏、創作、研究之水準，配合國家文化建設，貢獻社會。",
    "捐助方法": "由陳棟、謝武弘、朱宗慶等人捐助",
    "許可機關日期": "教育部台社字第17257號函",
    "存立時期": "永久",
    "財產總額": "1000000",
    "結案原因": "准許",
    "結案日期": "097\/07\/16",
    "歸檔日期": "097\/09\/22",
    "發證日期": "097\/07\/24",
    "送達代收人姓名": "",
    "送達代收人住址": "",
    "郵遞區號": "",
    "清算人": "",
    "註銷日期": "",
    "撤銷日期": "",
    "撤(註)銷機關文號": "",
    "撤(註)銷原因": "",
    "董監事": [
        [
            "監事",
            "劉本固"
        ],
        [
            "董事長",
            "劉叔康"
        ],
        [
            "董事",
            "林炳興"
        ],
        [
            "監事",
            "宋俊錚"
        ],
        [
            "監事",
            "林怡昕"
        ],
        [
            "董事",
            "陳麗娟"
        ],
        [
            "董事",
            "陳曉業"
        ],
        [
            "董事",
            "藍漢民"
        ]
    ],
    "分事務所": [

    ],
    "latitude": "",
    "longitude": ""
}