{
    "url": {
        "data": "http:\/\/cdcb.judicial.gov.tw\/abbs\/wkw\/WHD6K03.jsp?ab=AAAdkxAAHAAACgiAAI&bc=061&cd=%AA%6B%B5%6E++++++++++++++++&de=000481&ef=TPD&fg=1",
        "staff": "http:\/\/cdcb.judicial.gov.tw\/abbs\/wkw\/WHD6K04.jsp?ab=AAAdkxAAHAAACgiAAI&bc=061&cd=%AA%6B%B5%6E++++++++++++++++&de=000481&ef=TPD&fg=1",
        "office": "http:\/\/cdcb.judicial.gov.tw\/abbs\/wkw\/WHD6K07.jsp?ab=AAAdkxAAHAAACgiAAI&bc=061&cd=%AA%6B%B5%6E++++++++++++++++&de=000481&ef=TPD&fg=1"
    },
    "登記案號": "061年法登字481號",
    "類別": "財團",
    "案由": "設立登記",
    "主任": "林貴美",
    "登記號數": "481",
    "收件日期": "061\/11\/02",
    "登記日期": "061\/11\/02",
    "公告日期": "061\/11\/02",
    "登記簿": "27冊17頁",
    "任期判定": "",
    "屆期判定": "0",
    "法人代表": "胡維藩",
    "法人名稱": "財團法人詩文橋藝中心",
    "設立登記日期": "061\/11\/02",
    "主事務所": "台北市錦州街十八號二樓",
    "目的": "為響應復興固有文化，陶冶高尚情藻，啟發智能，培植詩才提倡橋藝等各種正當娛樂。",
    "捐助方法": "發起人捐獻及有關事業及孳息等收入",
    "許可機關日期": "中華民國六十一年有二十七日",
    "存立時期": "永久",
    "財產總額": "100000",
    "結案原因": "准許",
    "結案日期": "061\/11\/02",
    "歸檔日期": "061\/11\/02",
    "發證日期": "",
    "送達代收人姓名": "",
    "送達代收人住址": "",
    "郵遞區號": "",
    "清算人": "",
    "註銷日期": "",
    "撤銷日期": "",
    "撤(註)銷機關文號": "",
    "撤(註)銷原因": "",
    "董監事": [
        [
            "董事長",
            "胡維藩"
        ]
    ],
    "分事務所": [

    ],
    "latitude": "",
    "longitude": ""
}