{
    "登記案號": "099年法登社字26號",
    "類別": "社團",
    "案由": "設立登記",
    "主任": "李秋瓊",
    "登記號數": "1814",
    "收件日期": "099\/03\/29",
    "登記日期": "099\/03\/29",
    "公告日期": "099\/03\/29",
    "登記簿": "37冊34頁",
    "任期判定": "",
    "屆期判定": "",
    "法人代表": "郭忠奇",
    "法人名稱": "社團法人台灣亞洲國企人協會",
    "設立登記日期": "099\/03\/29",
    "主事務所": "臺中縣潭子鄉大富路三段３３巷１１８弄１２號",
    "目的": "本會以促進會員之聯誼與加強大專院校與國、內外產業界之產學交流為宗旨。",
    "捐助方法": "會員會費等",
    "許可機關日期": "內政部中華民國９８年６月５日台內社字第0980104496號函",
    "存立時期": "永久",
    "財產總額": "31200",
    "結案原因": "准許",
    "結案日期": "099\/03\/29",
    "歸檔日期": "099\/04\/07",
    "發證日期": "099\/03\/31",
    "送達代收人姓名": "劉珂均",
    "送達代收人住址": "電話:0425883809",
    "郵遞區號": "",
    "清算人": "",
    "註銷日期": "",
    "撤銷日期": "",
    "撤(註)銷機關文號": "",
    "撤(註)銷原因": "",
    "董監事": [
        [
            "理事長",
            "郭忠奇"
        ],
        [
            "常務理事",
            "林素惠"
        ],
        [
            "常務理事",
            "湯火論"
        ],
        [
            "理事",
            "李泉盛"
        ],
        [
            "理事",
            "陳宏彰"
        ],
        [
            "理事",
            "黃烈堂"
        ],
        [
            "理事",
            "陳豐能"
        ],
        [
            "理事",
            "張光宇"
        ],
        [
            "常務監事",
            "吳敏弘"
        ]
    ],
    "分事務所": [

    ]
}