{
    "登記案號": "088年法登他字209號",
    "類別": "財團",
    "案由": "變更登記",
    "主任": "簡福助",
    "登記號數": "440032",
    "收件日期": "088\/12\/20",
    "登記日期": "088\/12\/21",
    "公告日期": "088\/12\/23",
    "登記簿": "1冊19頁",
    "任期判定": "2",
    "屆期判定": "10",
    "法人代表": "趙榮發",
    "法人名稱": "財團法人台北縣私立樂山療養院",
    "設立登記日期": "083\/04\/18",
    "主事務所": "台北縣八里鄉長坑村長坑口二十一號",
    "目的": "以基督博愛精神，推行社會公益，創辦慈善及教育事業服務社會以非營利為宗旨。",
    "捐助方法": "由國內外教會及善心人士捐助",
    "許可機關日期": "台北縣政府44.4.9社救字第五號",
    "存立時期": "永久",
    "財產總額": "282037",
    "結案原因": "准許",
    "結案日期": "088\/12\/21",
    "歸檔日期": "088\/12\/29",
    "發證日期": "088\/12\/29",
    "送達代收人姓名": "",
    "送達代收人住址": "",
    "郵遞區號": "",
    "清算人": "",
    "註銷日期": "",
    "撤銷日期": "",
    "撤(註)銷機關文號": "",
    "撤(註)銷原因": "",
    "董監事": [
        [
            "董事長",
            "趙榮發"
        ],
        [
            "常務董事",
            "黃文聰"
        ],
        [
            "常務董事",
            "蘇希宗"
        ],
        [
            "常務董事",
            "鄭信真"
        ],
        [
            "常務董事",
            "李燦然"
        ],
        [
            "董事",
            "胡茂生"
        ],
        [
            "董事",
            "郭維租"
        ],
        [
            "董事",
            "林明穱"
        ],
        [
            "董事",
            "沈淵瑤"
        ],
        [
            "董事",
            "許世珍"
        ],
        [
            "董事",
            "施麗月"
        ],
        [
            "董事",
            "林耕嶺"
        ],
        [
            "董事",
            "高俊明"
        ]
    ],
    "分事務所": [

    ]
}