{
    "url": {
        "data": "http:\/\/cdcb.judicial.gov.tw\/abbs\/wkw\/WHD6K03.jsp?ab=AAAdkxAAHAAAGgNAAH&bc=073&cd=%B5%6E++++++++++++++++++&de=000033&ef=TPD&fg=1",
        "staff": "http:\/\/cdcb.judicial.gov.tw\/abbs\/wkw\/WHD6K04.jsp?ab=AAAdkxAAHAAAGgNAAH&bc=073&cd=%B5%6E++++++++++++++++++&de=000033&ef=TPD&fg=1",
        "office": "http:\/\/cdcb.judicial.gov.tw\/abbs\/wkw\/WHD6K07.jsp?ab=AAAdkxAAHAAAGgNAAH&bc=073&cd=%B5%6E++++++++++++++++++&de=000033&ef=TPD&fg=1"
    },
    "登記案號": "073年登字33號",
    "類別": "財團",
    "案由": "設立登記",
    "主任": "陳淑敏",
    "登記號數": "1040",
    "收件日期": "073\/02\/24",
    "登記日期": "073\/02\/24",
    "公告日期": "073\/02\/24",
    "登記簿": "45冊57頁",
    "任期判定": "",
    "屆期判定": "",
    "法人代表": "殷張蘭熙",
    "法人名稱": "財團法人吳魯芹紀念基金會",
    "設立登記日期": "073\/02\/24",
    "主事務所": "台北市忠孝東路4段290號11樓",
    "目的": "本會以獎助文藝作品為目的。",
    "捐助方法": "自由捐助，由聯合報、中國時報、大陸工程股份有限公司各捐助新台幣貳拾萬元、其他社會人士籌集貳拾萬元，嗣後繼續籌集",
    "許可機關日期": "臺北市政府教育局中華民國73年1月24日北市教四字第2743號函",
    "存立時期": "永久",
    "財產總額": "800000",
    "結案原因": "准許",
    "結案日期": "073\/02\/24",
    "歸檔日期": "073\/04\/06",
    "發證日期": "073\/03\/01",
    "送達代收人姓名": "",
    "送達代收人住址": "",
    "郵遞區號": "",
    "清算人": "",
    "註銷日期": "",
    "撤銷日期": "",
    "撤(註)銷機關文號": "",
    "撤(註)銷原因": "",
    "董監事": [
        [
            "董事長",
            "殷張蘭熙"
        ],
        [
            "董事",
            "姚朋"
        ],
        [
            "董事",
            "王慶麟"
        ],
        [
            "董事",
            "金煒"
        ],
        [
            "董事",
            "劉宗向"
        ],
        [
            "董事",
            "張佛千"
        ],
        [
            "董事",
            "羅齊邦媛"
        ],
        [
            "董事",
            "吳葆珠"
        ],
        [
            "董事",
            "吳允絢"
        ]
    ],
    "分事務所": [

    ],
    "latitude": "",
    "longitude": ""
}