{
    "登記案號": "102年法登社字57號",
    "類別": "社團",
    "案由": "設立登記",
    "主任": "李秋瓊",
    "登記號數": "2215",
    "收件日期": "102\/08\/07",
    "登記日期": "102\/08\/07",
    "公告日期": "102\/08\/07",
    "登記簿": "44冊14頁",
    "任期判定": "",
    "屆期判定": "",
    "法人代表": "張悟廣",
    "法人名稱": "社團法人台灣社福慈善聖業協會",
    "設立登記日期": "102\/08\/07",
    "主事務所": "臺中市太平區太平路350號3樓",
    "目的": "為弘揚佛陀慈悲和上帝博愛精神，擁護政府、關懷弱勢，確實改善經濟環境，消除貧困，提升生活文化品質。促進家庭美滿幸福，增進社會福利。保障弱勢的權益為宗旨。",
    "捐助方法": "會員會費等",
    "許可機關日期": "內政部中華民國102年7月10日台內社字第1020245985號函",
    "存立時期": "永久",
    "財產總額": "1000",
    "結案原因": "准許",
    "結案日期": "102\/08\/07",
    "歸檔日期": "",
    "發證日期": "102\/08\/08",
    "送達代收人姓名": "張悟廣",
    "送達代收人住址": "電話：0988-327399",
    "郵遞區號": "",
    "清算人": "",
    "註銷日期": "",
    "撤銷日期": "",
    "撤(註)銷機關文號": "",
    "撤(註)銷原因": "",
    "董監事": [
        [
            "理事長",
            "張悟廣"
        ],
        [
            "副理事長",
            "吳冠真"
        ],
        [
            "常務理事",
            "陳振吉"
        ],
        [
            "理事",
            "張政和"
        ],
        [
            "理事",
            "倪若蘭"
        ],
        [
            "理事",
            "李韻華"
        ],
        [
            "理事",
            "呂麗妍"
        ],
        [
            "理事",
            "張政達"
        ],
        [
            "理事",
            "楊延壽"
        ],
        [
            "監事長",
            "江妮諺"
        ]
    ],
    "分事務所": [

    ],
    "latitude": "24.124117000000",
    "longitude": "120.717098300000"
}