{
    "url": {
        "data": "http:\/\/cdcb.judicial.gov.tw\/abbs\/wkw\/WHD6K03.jsp?ab=AAAdkxAAHAAAE2%2BAAA&bc=089&cd=%AA%6B%B5%6E%A5%4C++++++++++++++&de=000001&ef=SLD&fg=1",
        "staff": "http:\/\/cdcb.judicial.gov.tw\/abbs\/wkw\/WHD6K04.jsp?ab=AAAdkxAAHAAAE2%2BAAA&bc=089&cd=%AA%6B%B5%6E%A5%4C++++++++++++++&de=000001&ef=SLD&fg=1",
        "office": "http:\/\/cdcb.judicial.gov.tw\/abbs\/wkw\/WHD6K07.jsp?ab=AAAdkxAAHAAAE2%2BAAA&bc=089&cd=%AA%6B%B5%6E%A5%4C++++++++++++++&de=000001&ef=SLD&fg=1"
    },
    "登記案號": "089年法登他字1號",
    "類別": "財團",
    "案由": "變更登記",
    "主任": "簡福助",
    "登記號數": "490098",
    "收件日期": "089\/01\/03",
    "登記日期": "089\/01\/04",
    "公告日期": "089\/01\/05",
    "登記簿": "1冊45頁",
    "任期判定": "1",
    "屆期判定": "12",
    "法人代表": "李燦然",
    "法人名稱": "財團法人台灣省台北縣私立淡江高級中學",
    "設立登記日期": "083\/11\/29",
    "主事務所": "台北縣淡水鎮真理街二十六號",
    "目的": "為辦理台北縣私立淡江高級中學暨附設國民中學部、私立純德幼稚園。",
    "捐助方法": "捐助",
    "許可機關日期": "台灣省政府教育廳47.11.18教二字第六三四四六號函",
    "存立時期": "永久",
    "財產總額": "102436612",
    "結案原因": "准許",
    "結案日期": "089\/01\/04",
    "歸檔日期": "089\/01\/14",
    "發證日期": "089\/01\/14",
    "送達代收人姓名": "",
    "送達代收人住址": "",
    "郵遞區號": "",
    "清算人": "",
    "註銷日期": "",
    "撤銷日期": "",
    "撤(註)銷機關文號": "",
    "撤(註)銷原因": "",
    "董監事": [
        [
            "董事長",
            "李燦然"
        ],
        [
            "董事",
            "郭德士"
        ],
        [
            "董事",
            "林忠義"
        ],
        [
            "董事",
            "黃淑丹"
        ],
        [
            "董事",
            "楊約西"
        ],
        [
            "董事",
            "陳福住"
        ],
        [
            "董事",
            "簡安硌"
        ],
        [
            "董事",
            "溫宏欣"
        ],
        [
            "董事",
            "徐良杰"
        ],
        [
            "董事",
            "廖明發"
        ],
        [
            "董事",
            "黃昭弘"
        ],
        [
            "董事",
            "徐聖峰"
        ],
        [
            "董事",
            "林玉美"
        ]
    ],
    "分事務所": [

    ],
    "latitude": "",
    "longitude": ""
}