{
    "登記案號": "102年法登他字604號",
    "類別": "財團",
    "案由": "變更登記",
    "主任": "楊志純",
    "登記號數": "27",
    "收件日期": "102\/05\/29",
    "登記日期": "102\/05\/29",
    "公告日期": "102\/05\/29",
    "登記簿": "2冊28頁",
    "任期判定": "1",
    "屆期判定": "16",
    "法人代表": "麥明康",
    "法人名稱": "財團法人美南浸信會台北市事務所",
    "設立登記日期": "043\/08\/12",
    "主事務所": "台北市中正區懷寧街47之1號",
    "目的": "本法人宗旨為在台灣及台灣以外地區研討企劃、推行基督教義、勉勵教友崇信上帝，辦理社會慈善及救助事業；並為在美國維吉尼亞州之美南浸信會國際傳道部在世界各地推進其宣揚基督福音及社會慈善救助事業。",
    "捐助方法": "美南浸信會捐助",
    "許可機關日期": "台灣省政府四十三年一月十四日　（四三）府民一字第一四九００號函",
    "存立時期": "永久",
    "財產總額": "685663265",
    "結案原因": "准許",
    "結案日期": "102\/05\/29",
    "歸檔日期": "",
    "發證日期": "102\/06\/05",
    "送達代收人姓名": "",
    "送達代收人住址": "",
    "郵遞區號": "",
    "清算人": "",
    "註銷日期": "",
    "撤銷日期": "",
    "撤(註)銷機關文號": "",
    "撤(註)銷原因": "",
    "董監事": [
        [
            "董事",
            "艾思福"
        ],
        [
            "董事",
            "蘇明"
        ],
        [
            "董事長",
            "麥明康"
        ],
        [
            "董事",
            "葛振明"
        ],
        [
            "董事",
            "黃國興"
        ],
        [
            "董事",
            "張福德"
        ],
        [
            "董事",
            "謝振理"
        ]
    ],
    "分事務所": [

    ]
}