{
    "登記案號": "096年法登他字786號",
    "類別": "社團",
    "案由": "變更登記",
    "主任": "陳茂哲",
    "登記號數": "412",
    "收件日期": "096\/08\/17",
    "登記日期": "096\/08\/23",
    "公告日期": "096\/08\/23",
    "登記簿": "15冊1頁",
    "任期判定": "1",
    "屆期判定": "8",
    "法人代表": "喻肇青",
    "法人名稱": "社團法人中華民國專業者都市改革組織",
    "設立登記日期": "083\/12\/02",
    "主事務所": "台北市大安區羅斯福路3段61號2樓",
    "目的": "基於社會正義與公平之理想，本民主、理性、和平之原則，團結相關專業者及社會人士，協助政府及人民改善都市問題，並促進全民公平合理使用都市空間的權利。",
    "捐助方法": "??J會費??g常會費??晪U會費??瓣[會員??~費?鸕|員捐助?攭e託收益?鰲F息收入?魒銗L收入",
    "許可機關日期": "內政部八十一年四月廿四日台︵八十一︶內社字第八一七九八０六號函",
    "存立時期": "永久",
    "財產總額": "136500",
    "結案原因": "准許",
    "結案日期": "096\/08\/23",
    "歸檔日期": "097\/08\/29",
    "發證日期": "096\/08\/31",
    "送達代收人姓名": "",
    "送達代收人住址": "",
    "郵遞區號": "",
    "清算人": "",
    "註銷日期": "",
    "撤銷日期": "",
    "撤(註)銷機關文號": "",
    "撤(註)銷原因": "",
    "董監事": [
        [
            "監事",
            "劉可強"
        ],
        [
            "理事",
            "劉欣蓉"
        ],
        [
            "常務理事",
            "黃麗玲"
        ],
        [
            "常務理事",
            "陳育貞"
        ],
        [
            "理事",
            "康旻杰"
        ],
        [
            "理事",
            "呂欽文"
        ],
        [
            "理事",
            "黃瑞茂"
        ],
        [
            "監事",
            "黃衍明"
        ],
        [
            "理事",
            "顏亮一"
        ],
        [
            "理事",
            "彭揚凱"
        ],
        [
            "理事",
            "劉柏宏"
        ],
        [
            "理事",
            "王耀東"
        ],
        [
            "監事",
            "王立甫"
        ],
        [
            "理事",
            "左昭德"
        ],
        [
            "常務理事",
            "王鴻楷"
        ],
        [
            "理事",
            "邱詠婷"
        ],
        [
            "常務監事",
            "夏鑄九"
        ]
    ],
    "分事務所": [

    ],
    "latitude": "",
    "longitude": ""
}