{
    "登記案號": "089年法登社字2號",
    "類別": "社團",
    "案由": "設立登記",
    "主任": "羅培昌",
    "登記號數": "210",
    "收件日期": "089\/03\/20",
    "登記日期": "089\/04\/05",
    "公告日期": "089\/04\/05",
    "登記簿": "4冊91頁",
    "任期判定": "",
    "屆期判定": "0",
    "法人代表": "沈優勝",
    "法人名稱": "社團法人中國玉清覺修協會",
    "設立登記日期": "089\/04\/05",
    "主事務所": "彰化縣員林鎮員水路一段二四二號",
    "目的": "結合社會有心從事研究中華道統哲學思想及道德文化、改善人本善之精神思想協助政府淨化人心邁向世界大同之境地。",
    "捐助方法": "會員會費及其它捐助",
    "許可機關日期": "內政部八十六年一月十二日",
    "存立時期": "永久",
    "財產總額": "981921",
    "結案原因": "准許",
    "結案日期": "089\/04\/06",
    "歸檔日期": "092\/12\/09",
    "發證日期": "",
    "送達代收人姓名": "",
    "送達代收人住址": "",
    "郵遞區號": "",
    "清算人": "",
    "註銷日期": "",
    "撤銷日期": "",
    "撤(註)銷機關文號": "",
    "撤(註)銷原因": "",
    "董監事": [
        [
            "理事長",
            "沈優勝"
        ],
        [
            "常務理事",
            "謝文堂"
        ],
        [
            "常務理事",
            "許盛昌"
        ],
        [
            "常務理事",
            "林正義"
        ],
        [
            "常務理事",
            "李政芳"
        ],
        [
            "理事",
            "王中皇"
        ],
        [
            "理事",
            "李一夫"
        ],
        [
            "理事",
            "謝煥文"
        ],
        [
            "理事",
            "蕭煌基"
        ],
        [
            "理事",
            "張紹銓"
        ],
        [
            "理事",
            "邱秋喜"
        ],
        [
            "理事",
            "葉承澤"
        ],
        [
            "理事",
            "江應從"
        ],
        [
            "理事",
            "黃新吾"
        ],
        [
            "常務監事",
            "林志能"
        ],
        [
            "監事",
            "沈正良"
        ],
        [
            "監事",
            "林欽賢"
        ],
        [
            "監事",
            "鍾啟文"
        ]
    ],
    "分事務所": [

    ],
    "latitude": "",
    "longitude": ""
}