{
    "登記案號": "102年法登他字1223號",
    "類別": "財團",
    "案由": "變更登記",
    "主任": "楊志純",
    "登記號數": "810",
    "收件日期": "102\/10\/23",
    "登記日期": "102\/10\/23",
    "公告日期": "102\/10\/23",
    "登記簿": "38冊15頁",
    "任期判定": "2",
    "屆期判定": "12",
    "法人代表": "各董事",
    "法人名稱": "財團法人國防工業發展基金會",
    "設立登記日期": "068\/05\/08",
    "主事務所": "台北市中正區博愛路164號",
    "目的": "為促進國防有關工業加速整體發展。",
    "捐助方法": "??蛘j救國捐獻及國內外公私團體或個人之捐獻。??F府循預算程序撥助款。??銗L收入",
    "許可機關日期": "行政院六十八年三月十日台︵六八︶財字第二二四九號函",
    "存立時期": "永久",
    "財產總額": "6129395715",
    "結案原因": "准許",
    "結案日期": "102\/10\/23",
    "歸檔日期": "",
    "發證日期": "102\/10\/31",
    "送達代收人姓名": "",
    "送達代收人住址": "",
    "郵遞區號": "",
    "清算人": "",
    "註銷日期": "",
    "撤銷日期": "",
    "撤(註)銷機關文號": "",
    "撤(註)銷原因": "",
    "董監事": [
        [
            "董事",
            "魏大鵬"
        ],
        [
            "董事",
            "張家祝"
        ],
        [
            "董事",
            "陳小紅"
        ],
        [
            "董事",
            "沈榮津"
        ],
        [
            "董事",
            "嚴德發"
        ],
        [
            "董事",
            "劉明津"
        ],
        [
            "董事",
            "廖榮鑫"
        ],
        [
            "董事長",
            "嚴明"
        ],
        [
            "董事",
            "徐秀滄"
        ],
        [
            "董事",
            "陳國榮"
        ],
        [
            "董事",
            "劉佩玲"
        ],
        [
            "董事",
            "李素瑛"
        ],
        [
            "監事主席",
            "石素梅"
        ],
        [
            "監事",
            "宋餘俠"
        ],
        [
            "監事",
            "邱昌嶽"
        ]
    ],
    "分事務所": [

    ]
}