{
    "登記案號": "089年法登他字102號",
    "類別": "財團",
    "案由": "變更登記",
    "主任": "林文鼎",
    "登記號數": "394",
    "收件日期": "089\/08\/28",
    "登記日期": "089\/08\/28",
    "公告日期": "089\/08\/29",
    "登記簿": "14冊21頁",
    "任期判定": "1",
    "屆期判定": "4",
    "法人代表": "蘇福履",
    "法人名稱": "財團法人台灣省中國基督教長老會台灣區會",
    "設立登記日期": "056\/07\/17",
    "主事務所": "台北縣土城市清水路二一八號",
    "目的": "以篤信聖經和長老會基本信條，闡揚基督真理，傳播十架寶血救恩，並創辦教會、學校、醫院、幼稚園等社會慈善公益事業為宗旨。",
    "捐助方法": "由中國基督教長老會會員及熱心人士捐助",
    "許可機關日期": "台灣省政府五十六年六月二十三日府民一字第四六六０七號通知",
    "存立時期": "永久",
    "財產總額": "2688000",
    "結案原因": "准許",
    "結案日期": "089\/08\/28",
    "歸檔日期": "",
    "發證日期": "",
    "送達代收人姓名": "",
    "送達代收人住址": "",
    "郵遞區號": "",
    "清算人": "",
    "註銷日期": "",
    "撤銷日期": "",
    "撤(註)銷機關文號": "",
    "撤(註)銷原因": "",
    "董監事": [
        [
            "董事長",
            "蘇福履"
        ],
        [
            "董事",
            "趙張阿英"
        ],
        [
            "董事",
            "林明輝"
        ],
        [
            "董事",
            "葉蒼榮"
        ],
        [
            "董事",
            "蕭志達"
        ]
    ],
    "分事務所": [

    ],
    "latitude": "",
    "longitude": ""
}