{
    "url": {
        "data": "http:\/\/cdcb.judicial.gov.tw\/abbs\/wkw\/WHD6K03.jsp?ab=AAAdkxAAHAAAOyMAAG&bc=100&cd=%AA%6B%B5%6E%A5%4C++++++++++++++&de=000209&ef=TCD&fg=1",
        "staff": "http:\/\/cdcb.judicial.gov.tw\/abbs\/wkw\/WHD6K04.jsp?ab=AAAdkxAAHAAAOyMAAG&bc=100&cd=%AA%6B%B5%6E%A5%4C++++++++++++++&de=000209&ef=TCD&fg=1",
        "office": "http:\/\/cdcb.judicial.gov.tw\/abbs\/wkw\/WHD6K07.jsp?ab=AAAdkxAAHAAAOyMAAG&bc=100&cd=%AA%6B%B5%6E%A5%4C++++++++++++++&de=000209&ef=TCD&fg=1"
    },
    "登記案號": "100年法登他字209號",
    "類別": "財團",
    "案由": "變更登記",
    "主任": "李秋瓊",
    "登記號數": "437",
    "收件日期": "100\/06\/08",
    "登記日期": "100\/06\/08",
    "公告日期": "100\/06\/08",
    "登記簿": "13冊18頁",
    "任期判定": "2",
    "屆期判定": "7",
    "法人代表": "賴正鎰",
    "法人名稱": "財團法人鄉林文教基金會",
    "設立登記日期": "079\/09\/04",
    "主事務所": "臺中市西區臺中港路一段３０４號１樓",
    "目的": "以倡導正當戶外休閒活動，提昇國民生活品質，舉辦教育公益業務為目的。",
    "捐助方法": "由賴正鎰等人捐助",
    "許可機關日期": "臺灣省政府教育廳中華民國７９年７月２６日",
    "存立時期": "永久",
    "財產總額": "1000000",
    "結案原因": "准許",
    "結案日期": "100\/06\/08",
    "歸檔日期": "100\/07\/05",
    "發證日期": "100\/06\/09",
    "送達代收人姓名": "何珍瑜",
    "送達代收人住址": "電話:0423296111轉803",
    "郵遞區號": "",
    "清算人": "",
    "註銷日期": "",
    "撤銷日期": "",
    "撤(註)銷機關文號": "",
    "撤(註)銷原因": "",
    "董監事": [
        [
            "董事長",
            "賴正鎰"
        ],
        [
            "董事",
            "張釿"
        ],
        [
            "董事",
            "陳金美"
        ],
        [
            "董事",
            "姜紹基"
        ],
        [
            "董事",
            "廖振利"
        ],
        [
            "董事",
            "林慶豐"
        ],
        [
            "董事",
            "洪勝義"
        ]
    ],
    "分事務所": [

    ],
    "latitude": "",
    "longitude": ""
}