{
    "登記案號": "103年法登他字11號",
    "類別": "社團",
    "案由": "變更登記",
    "主任": "塗文鎮",
    "登記號數": "208",
    "收件日期": "103\/02\/18",
    "登記日期": "103\/02\/18",
    "公告日期": "103\/02\/25",
    "登記簿": "5冊208頁",
    "任期判定": "2",
    "屆期判定": "4",
    "法人代表": "吳錦秀",
    "法人名稱": "社團法人花蓮縣彌勒大道弘慈會",
    "設立登記日期": "091\/01\/22",
    "主事務所": "花蓮縣玉里鎮忠智路七號",
    "目的": "本會係本彌勒古佛以「慈」為宗，皆大歡喜之精神，弘揚彌勒大道真義，推動淨化心靈環保，以期完成本會設立之目的與宗旨。",
    "捐助方法": "一、會員入會費：每人參佰元正。二、常年會費：每人每月壹佰元正。三、會員捐款。",
    "許可機關日期": "花蓮縣政府中華民國九十年十二月二十五日九十府社行字第一三九五七一號",
    "存立時期": "永久",
    "財產總額": "193000",
    "結案原因": "准許",
    "結案日期": "103\/02\/18",
    "歸檔日期": "",
    "發證日期": "",
    "送達代收人姓名": "",
    "送達代收人住址": "",
    "郵遞區號": "",
    "清算人": "",
    "註銷日期": "",
    "撤銷日期": "",
    "撤(註)銷機關文號": "",
    "撤(註)銷原因": "",
    "董監事": [
        [
            "理事",
            "邱貴久"
        ],
        [
            "常務理事",
            "吳存億"
        ],
        [
            "理事",
            "邱創椿"
        ],
        [
            "理事長",
            "吳錦秀"
        ],
        [
            "常務理事",
            "吳妙茵"
        ],
        [
            "理事",
            "陳清金"
        ],
        [
            "理事",
            "夏劉美莉"
        ],
        [
            "理事",
            "陳珮筠"
        ],
        [
            "理事",
            "林宜璟"
        ],
        [
            "常務監事",
            "張芸慈"
        ]
    ],
    "分事務所": [

    ]
}