{
    "登記案號": "088年法登他字176號",
    "類別": "財團",
    "案由": "變更登記",
    "主任": "吳永崑",
    "登記號數": "130",
    "收件日期": "088\/12\/28",
    "登記日期": "089\/01\/03",
    "公告日期": "089\/01\/03",
    "登記簿": "4冊25頁",
    "任期判定": "2",
    "屆期判定": "6",
    "法人代表": "黃金昆",
    "法人名稱": "財團法人中華道明會",
    "設立登記日期": "067\/09\/22",
    "主事務所": "高雄市建國一路三五四號",
    "目的": "宣揚推行天主教之教義及辦理慈善救濟事業、並協助政府發展教育為目的。",
    "捐助方法": "捐助",
    "許可機關日期": "台灣省政府民政廳、中華民國六十七年六月十九日。",
    "存立時期": "永久",
    "財產總額": "843056",
    "結案原因": "准許",
    "結案日期": "089\/01\/03",
    "歸檔日期": "089\/07\/03",
    "發證日期": "",
    "送達代收人姓名": "",
    "送達代收人住址": "",
    "郵遞區號": "",
    "清算人": "",
    "註銷日期": "",
    "撤銷日期": "",
    "撤(註)銷機關文號": "",
    "撤(註)銷原因": "",
    "董監事": [
        [
            "董事長",
            "黃金昆"
        ],
        [
            "董事",
            "徐清賢"
        ],
        [
            "董事",
            "潘貝頎"
        ],
        [
            "董事",
            "馮觀濤"
        ],
        [
            "董事",
            "陳紹基"
        ]
    ],
    "分事務所": [

    ],
    "latitude": 22.6334167,
    "longitude": 120.3227129
}